framawarp-0.1.2.dist-info/METADATA
framawarp-0.1.2.dist-info/WHEEL
framawarp-0.1.2.dist-info/licenses/LICENSE
framawarp/__init__.py
framawarp/enums.py
framawarp/exceptions.py
framawarp/frame.py
framawarp-0.1.2.dist-info/RECORD
