Metadata-Version: 2.1
Name: framawarp
Version: 0.1.2
Summary: Image manipulation on steroids
Author-Email: Mert Can Demir <validatedev@gmail.com>
License: MIT
Requires-Python: >=3.8
Requires-Dist: numpy>=1.24.4
Requires-Dist: torch>=2.0.0
Requires-Dist: opencv-python>=4.8.1.78
